aks.py
fermat.py
millerRabin.py
solovayStrassen.py
trialDivision.py
primeTester-1.1.dist-info/LICENSE
primeTester-1.1.dist-info/METADATA
primeTester-1.1.dist-info/WHEEL
primeTester-1.1.dist-info/top_level.txt
primeTester-1.1.dist-info/RECORD
