Metadata-Version: 2.1
Name: primeTester
Version: 1.1
Summary: A collection of Python modules consisting different primality tests.
Home-page: https://github.com/avrha/Prime-Tests
Author: Joey Ferenchak
Author-email: sjferenchak@gmail.com
License: UNKNOWN
Platform: UNKNOWN
Classifier: Programming Language :: Python :: 3
Classifier: License :: OSI Approved :: MIT License
Classifier: Operating System :: OS Independent
Requires-Python: >=3.6
